LICENSE
MANIFEST.in
setup.py
djnotty/__init__.py
djnotty/models.py
djnotty/notty_builder.py
djnotty/migrations/0001_initial.py
djnotty/migrations/0001_initial.pyc
djnotty/migrations/__init__.py
djnotty/migrations/__init__.pyc
djnotty/static/djnotty/css/progressbar.css
djnotty/static/djnotty/js/djami_progressbar.js
djnotty/static/djnotty/js/djnotty.js
djnotty/static/djnotty/js/jquery.noty.packaged.min.js
djnotty/static/djnotty/js/promise.js
djnotty/static/djnotty/js/themes/bootstrap.js
djnotty/static/djnotty/js/themes/default.js
djnotty/static/djnotty/js/themes/relax.js
djxami/__init__.py
djxami/models.py
djxami/urls.py
djxami/views.py
djxami.egg-info/PKG-INFO
djxami.egg-info/SOURCES.txt
djxami.egg-info/dependency_links.txt
djxami.egg-info/requires.txt
djxami.egg-info/top_level.txt
djxami/migrations/0001_initial.py
djxami/migrations/0001_initial.pyc
djxami/migrations/0002_auto_20160204_1556.py
djxami/migrations/0002_auto_20160204_1556.pyc
djxami/migrations/0003_message_stream.py
djxami/migrations/0003_message_stream.pyc
djxami/migrations/0004_auto_20160205_1603.py
djxami/migrations/0004_auto_20160205_1603.pyc
djxami/migrations/__init__.py
djxami/migrations/__init__.pyc
djxami/static/djxami/core.js
djxami/templates/djxami/init.html
djxami/templatetags/__init__.py
djxami/templatetags/__init__.pyc
djxami/templatetags/djxami.py
djxami/templatetags/djxami.pyc