Metadata-Version: 1.0
Name: djxami
Version: 0.0.3
Summary: Create popup notifications.
Home-page: https://github.com/xacce/djxami
Author: xacce
Author-email: UNKNOWN
License: MIT
Platform: UNKNOWN
